{
  "store": {
    "name": "Coles Supermarkets Australia Pty Ltd",
    "abn": "45 004 189 708",
    "phone": "08 6112 6300",
    "address": "340 - CS Victoria Park EAS"
  },
  "tax_invoice": {
    "invoice_number": "",
    "date": "13/12/2024"
  },
  "transaction": {
    "transaction_number": "65696971",
    "date_time": "13/12/2024 12:19",
    "team_member": "Assisted Checkout",
    "payment_method": "MASTERCARD",
    "approval_code": "001180692800",
    "amount": 19.0,
    "gst_included": 1.73
  },
  "items": [
    {
      "description": "Coles Roast Chicken with Leach",
      "price": 9.5,
      "gst_in_item": 0.73
    },
    {
      "description": "Mediterranean Salad Bowl 185g",
      "price": 9.5,
      "gst_in_item": 0.73
    }
  ],
  "totals": {
    "subtotal": 17.54,
    "gst_included": 1.73,
    "grand_total": 19.0
  },
  "notes": "Date format is in Australian format.",
  "categories": [],
  "scanned_on": "2025-01-06T11:53:23.830304"
}